test/__init__.py
test/test_all.py
test/test_checksums.py
test/test_cipher_suite_parser.py
test/test_decryptor.py
test/test_key_derivator.py
test/quic_tests/__init__.py
test/quic_tests/test_quic_decode.py
test/quic_tests/test_quic_decryptor.py
test/quic_tests/test_quic_frame.py
test/quic_tests/test_quic_key_generation.py
test/quic_tests/test_quic_tls_parser.py
tlexport/__init__.py
tlexport/about.py
tlexport/checksums.py
tlexport/cipher_suite_parser.py
tlexport/decryptor.py
tlexport/dpkt_dsb.py
tlexport/key.py
tlexport/key_derivator.py
tlexport/keylog_reader.py
tlexport/log.py
tlexport/main.py
tlexport/output_builder.py
tlexport/packet.py
tlexport/session.py
tlexport/tlsrecord.py
tlexport/tlsversion.py
tlexport/quic/__init__.py
tlexport/quic/quic_decode.py
tlexport/quic/quic_decryptor.py
tlexport/quic/quic_dissector.py
tlexport/quic/quic_frame.py
tlexport/quic/quic_key_generation.py
tlexport/quic/quic_output_builder.py
tlexport/quic/quic_packet.py
tlexport/quic/quic_session.py
tlexport/quic/quic_tls_parser.py
tlexport/quic/udp_output_builder.py
TLExport-0.9.dist-info/LICENSE
TLExport-0.9.dist-info/METADATA
TLExport-0.9.dist-info/WHEEL
TLExport-0.9.dist-info/entry_points.txt
TLExport-0.9.dist-info/top_level.txt
TLExport-0.9.dist-info/RECORD
