Metadata-Version: 2.1
Name: TLExport
Version: 0.9
Summary: TLExport (TLE) is a tool for decrypting TLS-Traffic and exporting the traffic into unencrypted TCP/UDP traffic
Home-page: https://github.com/fkie-cad/TLExport/
Author-email: daniel.baier@fkie.fraunhofer.de
License: GPL v3
Keywords: tls,decryption,network forensik,pcap,pcapng
Classifier: License :: OSI Approved :: GNU General Public License v3 (GPLv3)
Classifier: Operating System :: OS Independent
Classifier: Natural Language :: English
Classifier: Programming Language :: Python :: 3 :: Only
Classifier: Programming Language :: JavaScript
Classifier: Topic :: Security
Requires-Python: >=3.10
License-File: LICENSE
Requires-Dist: cryptography
Requires-Dist: dpkt
Requires-Dist: scapy
